{
  "fs": {
    "version": "0.1",
    "0.1": {
      "file": "wtm_fs-0.1.js",
      "md5": "e517df1f7138db1ee71da50e215b5c4e",
      "compatible": "0.3.5"
    },
    "author": "Alfredo Roman",
    "license": "ISC",
    "compatible": "0.3.5",
    "description": "Module for fs gestion",
    "lasted": "0.1"
  },
  "memo": {
    "version": "0.1",
    "0.1": {
      "file": "wtm_memo-0.1.js",
      "md5": "da9a66a1e5eb0e7821b6fd39760643e3",
      "compatible": "0.3.5"
    },
    "author": "Alfredo Roman",
    "license": "ISC",
    "compatible": "0.3.5",
    "description": "Module for control internal memory or Objects",
    "lasted": "0.1"
  },
  "npm": {
    "version": "0.1",
    "0.1": {
      "file": "wtm_npm-0.1.js",
      "md5": "7897d86823bb9865bd35b23aa0c2ccf9",
      "compatible": "0.3.6"
    },
    "author": "Alfredo",
    "description": "npm, module exec command npm in shell.",
    "compatible": "0.3.6",
    "lasted": "0.1"
  },
  "test": {
    "version": "0.2",
    "0.0": {
      "file": "wtm_test-0.0.js",
      "md5": "57d4a8a95e0029deb392da4c2e185438",
      "compatible": "0.3.5"
    },
    "0.1": {
      "file": "wtm_test-0.1.js",
      "md5": "83ad08f8cce9fdb06985049016d25243",
      "compatible": "0.3.5"
    },
    "author": "Alfredo Roman",
    "license": "ISC",
    "compatible": "0.3.5",
    "description": "Module for test automatic interval",
    "lasted": "0.2",
    "0.2": {
      "file": "wtm_test-0.2.js",
      "md5": "14333f352529ae46f5d30649a72bb9ba",
      "compatible": "0.3.5"
    }
  },
  "web": {
    "version": "0.1",
    "0.1": {
      "file": "wtm_web-0.1.js",
      "md5": "4a6d50eaab965819b7a424b32f1c2628",
      "compatible": "0.3.5"
    },
    "author": "Alfredo Roman",
    "license": "ISC",
    "compatible": "0.3.5",
    "description": "Module list router stack",
    "lasted": "0.1"
  },
  "wtee": {
    "version": "0.2",
    "0.1": {
      "file": "wtm_wtee-0.1.js",
      "md5": "e1f2d9d670267d299db81670341fb845",
      "compatible": "0.3.5"
    },
    "author": "Alfredo Roman",
    "license": "ISC",
    "compatible": "0.3.5",
    "description": "Module for EventEmitter simple gestion.",
    "lasted": "0.2",
    "0.2": {
      "file": "wtm_wtee-0.2.js",
      "md5": "109949225ab36fa575162585844a7e52",
      "compatible": "0.3.5"
    }
  },
  "swagger" : {
    "version": "0.1",
      "0.1": {
      "file": "wtm_swagger-0.1.js",
      "md5": "58f08656bd0834efa01852e6913483d3",
      "compatible": "0.3.5"
    },
      "0.2": {
	  "file": "wtm_swagger",
	  "md5": "2ce3e483ae7b7a49c335d3be271ed11a",
	  "compatible": "0.6.1",
	  "tar": "wtm_swagger-0.2.tar.gz"
      },
    "author": "Alfredo Roman",
    "license": "ISC",
    "compatible": "0.6.1",
    "description": "Module for swagger for APIs ",
    "lasted": "0.2"
  }
}
